preprocess_toolbox/__init__.py
preprocess_toolbox/base.py
preprocess_toolbox/cli.py
preprocess_toolbox/interface.py
preprocess_toolbox/models.py
preprocess_toolbox/processor.py
preprocess_toolbox/utils.py
preprocess_toolbox/dataset/__init__.py
preprocess_toolbox/dataset/cli.py
preprocess_toolbox/dataset/process.py
preprocess_toolbox/dataset/spatial.py
preprocess_toolbox/dataset/time.py
preprocess_toolbox/loader/__init__.py
preprocess_toolbox/loader/cli.py
preprocess_toolbox/loader/utils.py
preprocess_toolbox-0.0.4.dist-info/AUTHORS.md
preprocess_toolbox-0.0.4.dist-info/LICENSE
preprocess_toolbox-0.0.4.dist-info/METADATA
preprocess_toolbox-0.0.4.dist-info/WHEEL
preprocess_toolbox-0.0.4.dist-info/entry_points.txt
preprocess_toolbox-0.0.4.dist-info/top_level.txt
preprocess_toolbox-0.0.4.dist-info/RECORD
