Metadata-Version: 2.1
Name: preprocess_toolbox
Version: 0.0.4
Summary: A preprocessing toolbox for converting datasets into assets ready for ML based workloads
Author: British Antarctic Survey / Alan Turing Institute
Maintainer-email: James Byrne <digitalinnovation@bas.ac.uk>
License: MIT License
Project-URL: bugs, https://github.com/environmental-forecasting/preprocess_toolbox/issues
Project-URL: homepage, https://github.com/environmental-forecasting/preprocess_toolbox
Classifier: Development Status :: 3 - Alpha
Classifier: Environment :: Console
Classifier: Intended Audience :: Science/Research
Classifier: License :: OSI Approved :: MIT License
Classifier: Natural Language :: English
Classifier: Operating System :: POSIX
Classifier: Programming Language :: Python :: 3
Classifier: Programming Language :: Python :: 3.8
Classifier: Programming Language :: Python :: 3.9
Classifier: Programming Language :: Python :: 3.10
Classifier: Programming Language :: Python :: 3.11
Requires-Python: >=3.8
License-File: LICENSE
License-File: AUTHORS.md
Requires-Dist: download-toolbox>=0.0.5
Requires-Dist: orjson
Requires-Dist: pip>=23.3
Requires-Dist: rioxarray
Requires-Dist: scitools-iris
Requires-Dist: wheel>=0.38.1
Requires-Dist: xarray[io]
Provides-Extra: dev
Requires-Dist: watchdog; extra == "dev"
Requires-Dist: flake8; extra == "dev"
Requires-Dist: tox; extra == "dev"
Requires-Dist: coverage; extra == "dev"
Requires-Dist: twine; extra == "dev"
Requires-Dist: pytest; extra == "dev"
Requires-Dist: black; extra == "dev"
Requires-Dist: build; extra == "dev"
Requires-Dist: importlib-metadata; extra == "dev"
Requires-Dist: pre-commit; extra == "dev"
Provides-Extra: docs
Requires-Dist: mkdocs; extra == "docs"
Requires-Dist: mkdocstrings[python]; extra == "docs"
Requires-Dist: markdown-include; extra == "docs"
Requires-Dist: mkdocs-material; extra == "docs"
